{
  "vite/modulepreload-polyfill": [],
  "vite/preload-helper": [],
  "src/routes.js": [],
  "plugin-vue:export-helper": [],
  "src/App.vue": [],
  "node_modules/tailwindcss/tailwind.css": [],
  "src/main.js": [],
  "index.html": [],
  "node_modules/@vue/shared/dist/shared.esm-bundler.js": [
    "/assets/vendor.60e58654.js"
  ],
  "node_modules/@vue/reactivity/dist/reactivity.esm-bundler.js": [
    "/assets/vendor.60e58654.js"
  ],
  "node_modules/@vue/runtime-core/dist/runtime-core.esm-bundler.js": [
    "/assets/vendor.60e58654.js"
  ],
  "node_modules/@vue/runtime-dom/dist/runtime-dom.esm-bundler.js": [
    "/assets/vendor.60e58654.js"
  ],
  "node_modules/vue/dist/vue.runtime.esm-bundler.js": [
    "/assets/vendor.60e58654.js"
  ],
  "node_modules/vite-ssg/dist/chunk-OOHBVVVU.mjs": [
    "/assets/vendor.60e58654.js"
  ],
  "node_modules/vite-ssg/dist/chunk-3CXI7ORQ.mjs": [
    "/assets/vendor.60e58654.js"
  ],
  "node_modules/@vue/devtools-api/lib/esm/env.js": [
    "/assets/vendor.60e58654.js"
  ],
  "node_modules/@vue/devtools-api/lib/esm/const.js": [
    "/assets/vendor.60e58654.js"
  ],
  "node_modules/@vue/devtools-api/lib/esm/proxy.js": [
    "/assets/vendor.60e58654.js"
  ],
  "node_modules/@vue/devtools-api/lib/esm/api/api.js": [
    "/assets/vendor.60e58654.js"
  ],
  "node_modules/@vue/devtools-api/lib/esm/api/app.js": [
    "/assets/vendor.60e58654.js"
  ],
  "node_modules/@vue/devtools-api/lib/esm/api/component.js": [
    "/assets/vendor.60e58654.js"
  ],
  "node_modules/@vue/devtools-api/lib/esm/api/context.js": [
    "/assets/vendor.60e58654.js"
  ],
  "node_modules/@vue/devtools-api/lib/esm/api/hooks.js": [
    "/assets/vendor.60e58654.js"
  ],
  "node_modules/@vue/devtools-api/lib/esm/api/util.js": [
    "/assets/vendor.60e58654.js"
  ],
  "node_modules/@vue/devtools-api/lib/esm/api/index.js": [
    "/assets/vendor.60e58654.js"
  ],
  "node_modules/@vue/devtools-api/lib/esm/plugin.js": [
    "/assets/vendor.60e58654.js"
  ],
  "node_modules/@vue/devtools-api/lib/esm/index.js": [
    "/assets/vendor.60e58654.js"
  ],
  "node_modules/vue-router/dist/vue-router.esm-bundler.js": [
    "/assets/vendor.60e58654.js"
  ],
  "node_modules/@vueuse/head/dist/index.mjs": [
    "/assets/vendor.60e58654.js"
  ],
  "node_modules/vite-ssg/dist/index.mjs": [
    "/assets/vendor.60e58654.js"
  ],
  "../../../img/FAQ.png": [
    "/assets/Index.7dedd41a.js",
    "/assets/Index.34ef7255.css"
  ],
  "node_modules/@heroicons/vue/solid/esm/MenuIcon.js": [
    "/assets/Index.7dedd41a.js",
    "/assets/Index.34ef7255.css"
  ],
  "node_modules/@heroicons/vue/solid/esm/PhoneIcon.js": [
    "/assets/Index.7dedd41a.js",
    "/assets/Index.34ef7255.css"
  ],
  "src/components/BrandTypography.vue": [
    "/assets/Index.7dedd41a.js",
    "/assets/Index.34ef7255.css"
  ],
  "src/components/BrandLogoOnly.vue": [
    "/assets/Index.7dedd41a.js",
    "/assets/Index.34ef7255.css"
  ],
  "src/utils/contactPerson.js": [
    "/assets/Index.7dedd41a.js",
    "/assets/Index.34ef7255.css"
  ],
  "src/components/Navbar.vue?vue&type=style&index=0&scoped=true&lang.sass": [
    "/assets/Index.7dedd41a.js",
    "/assets/Index.34ef7255.css"
  ],
  "src/components/Navbar.vue": [
    "/assets/Index.7dedd41a.js",
    "/assets/Index.34ef7255.css"
  ],
  "src/components/Accordion.vue": [
    "/assets/Index.7dedd41a.js",
    "/assets/Index.34ef7255.css"
  ],
  "src/pages/Index.vue?vue&type=style&index=0&scoped=true&lang.sass": [
    "/assets/Index.7dedd41a.js",
    "/assets/Index.34ef7255.css"
  ],
  "src/pages/Index.vue": [
    "/assets/Index.7dedd41a.js",
    "/assets/Index.34ef7255.css"
  ],
  "node_modules/@heroicons/vue/outline/esm/AnnotationIcon.js": [
    "/assets/About.c8b11695.js",
    "/assets/About.41d6cfa5.css"
  ],
  "node_modules/@heroicons/vue/outline/esm/GlobeAltIcon.js": [
    "/assets/About.c8b11695.js",
    "/assets/About.41d6cfa5.css"
  ],
  "node_modules/@heroicons/vue/outline/esm/LightningBoltIcon.js": [
    "/assets/About.c8b11695.js",
    "/assets/About.41d6cfa5.css"
  ],
  "node_modules/@heroicons/vue/outline/esm/ScaleIcon.js": [
    "/assets/About.c8b11695.js",
    "/assets/About.41d6cfa5.css"
  ],
  "src/components/icons/ArrowDown.vue": [
    "/assets/About.c8b11695.js",
    "/assets/About.41d6cfa5.css"
  ],
  "src/components/icons/Instagram.vue": [
    "/assets/About.c8b11695.js",
    "/assets/About.41d6cfa5.css"
  ],
  "src/pages/About.vue?vue&type=style&index=0&lang.css": [
    "/assets/About.c8b11695.js",
    "/assets/About.41d6cfa5.css"
  ],
  "src/pages/About.vue": [
    "/assets/About.c8b11695.js",
    "/assets/About.41d6cfa5.css"
  ]
}